cobalt/__init__.py
cobalt/__main__.py
cobalt/_version.py
cobalt/api_wrapper.py
cobalt/array_utils.py
cobalt/build_graph.py
cobalt/cobalt_types.py
cobalt/config.py
cobalt/embedding_models.py
cobalt/empty_visualization_block.py
cobalt/event_bus.py
cobalt/feature_compare.py
cobalt/generate_data.py
cobalt/generate_tab_embeddings.py
cobalt/graph_utils.py
cobalt/multires_graph.py
cobalt/selection_details.py
cobalt/selection_manager.py
cobalt/set_license.py
cobalt/state.py
cobalt/styles.py
cobalt/tabular.py
cobalt/ui.py
cobalt/ui_utils.py
cobalt/visualization.py
cobalt/visualization_dialog.py
cobalt/warnings_handler.py
cobalt/workspace.py
cobalt/coloring/__init__.py
cobalt/coloring/color_map.py
cobalt/coloring/color_range.py
cobalt/coloring/color_spec.py
cobalt/coloring/color_ui.py
cobalt/coloring/histogram_dialog.py
cobalt/groups/__init__.py
cobalt/groups/failure_groups.py
cobalt/groups/group_details.py
cobalt/groups/groups_comparison.py
cobalt/groups/groups_ui.py
cobalt/groups/user_groups.py
cobalt/lab/ClassifierObserver.py
cobalt/lab/__init__.py
cobalt/lab/ambiguous.py
cobalt/lab/auto_insight.py
cobalt/lab/connected_components.py
cobalt/lab/fix_model.py
cobalt/lab/generalization_score.py
cobalt/lab/generate.py
cobalt/lab/generate_failure_modes.py
cobalt/lab/generate_interpretable_dataframe.py
cobalt/lab/model.py
cobalt/lab/neighborhood.py
cobalt/lab/neighbors.py
cobalt/lab/planespot.py
cobalt/lab/rf_embedding.py
cobalt/lab/sbert.py
cobalt/lab/topo_prediction.py
cobalt/metrics_ui/__init__.py
cobalt/metrics_ui/metrics_select.py
cobalt/metrics_ui/metrics_ui.py
cobalt/model_overview/__init__.py
cobalt/model_overview/confusion_matrix.py
cobalt/model_overview/model_overview_ui.py
cobalt/model_overview/statistics_table.py
cobalt/problem_group/__init__.py
cobalt/problem_group/autogroup.py
cobalt/problem_group/failure_group.py
cobalt/problem_group/group_labeling.py
cobalt/problem_group/merge_tree.py
cobalt/repositories/__init__.py
cobalt/repositories/graph_repository.py
cobalt_ai-0.3.9.dist-info/METADATA
cobalt_ai-0.3.9.dist-info/WHEEL
cobalt_ai-0.3.9.dist-info/licenses/LICENSE
cobalt_ai-0.3.9.dist-info/licenses/NOTICE
cobalt_ai-0.3.9.dist-info/RECORD
