Metadata-Version: 2.4
Name: cobalt-ai
Version: 0.3.9
Summary: ML model understanding and repair
Project-URL: homepage, https://cobalt.bluelightai.com
Project-URL: documentation, https://docs.cobalt.bluelightai.com
Author-email: BluelightAI <support@bluelightai.com>
License: BluelightAI Cobalt Commercial Trial License and Non-Commercial License 1.0.0
License-File: LICENSE
License-File: NOTICE
Classifier: Framework :: Jupyter
Classifier: Intended Audience :: Developers
Classifier: Intended Audience :: Science/Research
Classifier: License :: Other/Proprietary License
Classifier: Operating System :: Microsoft :: Windows
Classifier: Operating System :: POSIX
Classifier: Operating System :: Unix
Classifier: Programming Language :: Python
Classifier: Programming Language :: Python :: 3
Classifier: Programming Language :: Python :: 3 :: Only
Classifier: Programming Language :: Python :: 3.8
Classifier: Programming Language :: Python :: 3.9
Classifier: Programming Language :: Python :: 3.10
Classifier: Programming Language :: Python :: 3.11
Classifier: Programming Language :: Python :: 3.12
Classifier: Programming Language :: Python :: 3.13
Classifier: Programming Language :: Python :: Implementation :: CPython
Classifier: Topic :: Scientific/Engineering :: Artificial Intelligence
Classifier: Topic :: Scientific/Engineering :: Information Analysis
Classifier: Topic :: Scientific/Engineering :: Mathematics
Requires-Python: >=3.8
Requires-Dist: ipynbname
Requires-Dist: ipyvue<1.11
Requires-Dist: ipyvuetify
Requires-Dist: ipywidgets
Requires-Dist: landscape-widget<0.5,>=0.4.0
Requires-Dist: mapper-core==0.7.0
Requires-Dist: matplotlib
Requires-Dist: numba>=0.55.2
Requires-Dist: pyarrow!=16.1.*,!=17.*; sys_platform == 'darwin'
Requires-Dist: pyarrow; sys_platform != 'darwin'
Requires-Dist: pynndescent<0.6,>=0.5.11
Requires-Dist: requests
Requires-Dist: seaborn
Provides-Extra: dev
Requires-Dist: bump-my-version; extra == 'dev'
Requires-Dist: isort; extra == 'dev'
Requires-Dist: nbconvert; extra == 'dev'
Requires-Dist: nbqa; extra == 'dev'
Requires-Dist: openai==1.55.3; extra == 'dev'
Requires-Dist: pre-commit; extra == 'dev'
Requires-Dist: pytest-asyncio; extra == 'dev'
Requires-Dist: pytest-cov; extra == 'dev'
Requires-Dist: pytest-mock; extra == 'dev'
Requires-Dist: pytest-xdist; extra == 'dev'
Requires-Dist: ruff~=0.5.7; extra == 'dev'
Requires-Dist: secretum-sphinx-theme; extra == 'dev'
Requires-Dist: sphinx; extra == 'dev'
Requires-Dist: sphinx-copybutton; extra == 'dev'
Requires-Dist: sphinx-favicon; extra == 'dev'
Requires-Dist: sphinx-rtd-theme; extra == 'dev'
Requires-Dist: sphinx-tabs; extra == 'dev'
Provides-Extra: embeddings
Requires-Dist: sentence-transformers; extra == 'embeddings'
